{"data":{"books":{"edges":[{"node":{"excerpt":"Was für ein Schmöker Mich hat schier der Schlag getroffen, als ich das eBook auf meinem Reader das erste Mal geöffnet hatte: nahezu 110…","fields":{"slug":"/190429/"},"frontmatter":{"date":"29. 04. 2019","title":"Error","path":"/190429","author":"Neal Stephenson","tags":["fantasy"],"cover":{"publicURL":"/static/error-d062a728905077ebe08c856dbacb2681.png"}}}},{"node":{"excerpt":"Was für ein Schmöker","fields":{"slug":"/190530/"},"frontmatter":{"date":"29. 04. 2019","title":"Error","path":"/190429","author":"Neal Stephenson","tags":["fantasy"],"cover":null}}}]},"author":null},"pageContext":{"author":"Neal Stephenson"}}