{"data":{"site":{"siteMetadata":{"title":"mliebelt Starter Blog","author":"Markus Liebelt"}},"markdownRemark":{"id":"4b9977f0-3eed-5489-a30f-20975d3f7b09","excerpt":"Start einer vielbändigen Saga Ich hatte irgendwo die Empfehlung gelesen, was man in der Fantasy heute lesen müsse, und hatte mich dann entschlossen, einige…","html":"<h1>Start einer vielbändigen Saga</h1>\n<p>Ich hatte irgendwo die Empfehlung gelesen, was man in der Fantasy heute lesen müsse, und hatte mich dann entschlossen, einige Bände unserer Bibliothek zu spenden. Die Bücher kamen dann einige Zeit später, und also machte ich mich auf, die Saga anzugehen.</p>\n<p>Die Welt, in der wir hier leben, wir von den Drachenreitern am Leben gehalten. Diese sind damit beschäftigt, mit ihren Drachen (die sie ein Leben lang betreuen) die Athmosphäre von der drohenden Gefahr, den Fäden, reinzuhalten.</p>\n<p>Die Geschichten sind relativ übersichtlich, entwickeln sich meist langsam, und man merkt ihnen teils auch ihr Alter an. Die entstanden ab 1972 in enger Folge, und da hat sich die Welt schon einige Male gedreht. Trotzdem, ab und an leihe ich wieder einen Band aus, ich bin zur Zeit ungefähr bei 3 oder 4. D.h. es sind noch 13 zu lesen.</p>","frontmatter":{"title":"Die Drachenreiter von Pern: Die Welt der Drachen","author":"Anne McCaffrey","date":"09. 09. 2017","tags":["fantasy","reihe"],"isbn":"B01MQX4QSI","cover":{"publicURL":"/static/drachenreiter-a0d684367f46adc7297714e951dee5f0.png"}}}},"pageContext":{"slug":"/170909/","previous":{"fields":{"slug":"/150821/"},"frontmatter":{"title":"Der Name des Windes","path":"/150821","tags":["fantasy","reihe"],"posttype":"book","author":"Patrick Rothfuss"}},"next":{"fields":{"slug":"/171015/"},"frontmatter":{"title":"Kriegsklingen","path":"/171015","tags":["fantasy","reihe"],"posttype":"book","author":"Joe Abercrombie"}}}}